odoo/addons/slow_statement_logger/README.rst
odoo/addons/slow_statement_logger/__init__.py
odoo/addons/slow_statement_logger/__manifest__.py
odoo/addons/slow_statement_logger/i18n/ca.po
odoo/addons/slow_statement_logger/i18n/it.po
odoo/addons/slow_statement_logger/i18n/slow_statement_logger.pot
odoo/addons/slow_statement_logger/readme/CONTRIBUTORS.md
odoo/addons/slow_statement_logger/readme/DESCRIPTION.md
odoo/addons/slow_statement_logger/readme/USAGE.md
odoo/addons/slow_statement_logger/static/description/icon.png
odoo/addons/slow_statement_logger/static/description/index.html
odoo_addon_slow_statement_logger-17.0.1.0.0.2.dist-info/METADATA
odoo_addon_slow_statement_logger-17.0.1.0.0.2.dist-info/WHEEL
odoo_addon_slow_statement_logger-17.0.1.0.0.2.dist-info/top_level.txt
odoo_addon_slow_statement_logger-17.0.1.0.0.2.dist-info/RECORD
